[
  {"code": "MDPD9NWBI", "credits": 10},
  {"code": "VEI18YQ447P", "credits": 10},
  {"code": "NS3ZS84YYJQ", "credits": 10},
  {"code": "9CFBLQ9VUEV", "credits": 10},
  {"code": "7BLVAP3JTT", "credits": 10},
  {"code": "GCS1U4PB7IS", "credits": 10},
  {"code": "DTLKS55LOI", "credits": 10},
  {"code": "ONI1TWOCLBH", "credits": 10},
  {"code": "C2J4HHWKOT6", "credits": 10},
  {"code": "1RVAR2ICXIM", "credits": 10},
  {"code": "SKKMEPF4H1P", "credits": 10},
  {"code": "I0ZZBELXLCE", "credits": 10},
  {"code": "0XDH1LWSJDM", "credits": 10},
  {"code": "YJYNTQ4Z7T", "credits": 10},
  {"code": "2ZOFRZAGYN", "credits": 10},
  {"code": "R6DBQK7TXUR", "credits": 10},
  {"code": "011IW0OSKULIN", "credits": 10},
  {"code": "QM06N1Y9TV", "credits": 10},
  {"code": "1TPVEGU0GJ8", "credits": 10},
  {"code": "ZSLK8RR91M9", "credits": 10},
  {"code": "O4I7E13ZX1C", "credits": 10},
  {"code": "F2432K85TFF", "credits": 10},
  {"code": "EFQ3MK5GY8U", "credits": 10},
  {"code": "WHUZSVSMRDP", "credits": 10},
  {"code": "0B1X25D4A7G6", "credits": 10},
  {"code": "M9FTDSHEJ8N", "credits": 10},
  {"code": "Y0W3CE5J31O", "credits": 10},
  {"code": "R0G8E9PC14K", "credits": 10},
  {"code": "LM50X7KMAQA", "credits": 10},
  {"code": "Z9SJRDQB8F", "credits": 10},
  {"code": "97HKKLL5CUK", "credits": 10},
  {"code": "OV3LSVOJYDQ", "credits": 10},
  {"code": "31KFXPUUTE3", "credits": 10},
  {"code": "6EIQ9JE3TVN", "credits": 10},
  {"code": "KWOTRGATACI", "credits": 10},
  {"code": "5XPLI33NRJ", "credits": 10},
  {"code": "P1MAJ5R67U", "credits": 10},
  {"code": "36F75YP1MPV", "credits": 10},
  {"code": "ZFFZ0YRSXE", "credits": 10},
  {"code": "MP2WLXWTPE", "credits": 10},
  {"code": "J5XJGGVPP2E", "credits": 10},
  {"code": "1ZOB77M6ZYB", "credits": 10},
  {"code": "ZX70E6PTFU", "credits": 10},
  {"code": "IIAL13KQHVI", "credits": 10},
  {"code": "CSP992BBYX8", "credits": 10},
  {"code": "WUCXQ5N6P1", "credits": 10},
  {"code": "LDZCQKBC4AF", "credits": 10},
  {"code": "MRJ6P3VT5FR", "credits": 10},
  {"code": "HJ0QMURRRR9", "credits": 10},
  {"code": "JADPNUABKBR", "credits": 10},
  {"code": "LRZT0N6CXWN", "credits": 100},
  {"code": "N01E6FH2UVB", "credits": 100},
  {"code": "H8V7SINUNGL", "credits": 100},
  {"code": "UXK5XAB8H0D", "credits": 100},
  {"code": "5CTND0CH5ZS", "credits": 100},
  {"code": "5RMNV44FIPL", "credits": 100},
  {"code": "ZV9WHBAPKP", "credits": 100},
  {"code": "UJJLUIAAL8", "credits": 100},
  {"code": "732ZH77YDS6", "credits": 100},
  {"code": "OIFKBW831W", "credits": 100},
  {"code": "TN1TSSVWRJJ", "credits": 100},
  {"code": "EI9R8MZW7UR", "credits": 100},
  {"code": "H38VHDYZ6E", "credits": 100},
  {"code": "TZ0J6OJKGJO", "credits": 100},
  {"code": "VRPLUSZ9DV", "credits": 100},
  {"code": "4ZECNF5HC47", "credits": 100},
  {"code": "2M5SLM15RM4", "credits": 100},
  {"code": "D6NFW8PB7HT", "credits": 100},
  {"code": "A4FUPWLJQYR", "credits": 100},
  {"code": "FTY4E4DPW29", "credits": 100},
  {"code": "YBGYVJK9ZT", "credits": 100},
  {"code": "RMOJEL0332", "credits": 100},
  {"code": "NA9DFC6XREC", "credits": 100},
  {"code": "LPWOXMBBV7L", "credits": 100},
  {"code": "ZLP3G10O0ZB", "credits": 100},
  {"code": "F1E1KQGWML", "credits": 100},
  {"code": "7QH0RZE32SX", "credits": 100},
  {"code": "IEI6Z6K96TD", "credits": 100},
  {"code": "00DB2YRNG3WDQ", "credits": 100},
  {"code": "NLLEPEJGQLL", "credits": 100},
  {"code": "09YUASY1W74W", "credits": 100},
  {"code": "7JRAJV6NMV", "credits": 100},
  {"code": "5OSJKNBZQLC", "credits": 100},
  {"code": "2X6URLX8YH8", "credits": 100},
  {"code": "AGWJTOCRNH7", "credits": 100},
  {"code": "U07SAIHL0A", "credits": 100},
  {"code": "5XZI4QAFUI9", "credits": 100},
  {"code": "4NYGA461HXM", "credits": 100},
  {"code": "ZVPYC3I7KP", "credits": 100},
  {"code": "49WHBAG3LL5", "credits": 100},
  {"code": "EAEMFC0L4Q5", "credits": 100},
  {"code": "OV7FF5XPA9N", "credits": 100},
  {"code": "6L153ZYAQV", "credits": 100},
  {"code": "TA3XA5QMUEO", "credits": 100},
  {"code": "P9N13U5VKRK", "credits": 100},
  {"code": "NG4M8NFKQ9C", "credits": 100},
  {"code": "TV9EAGRSB5", "credits": 100},
  {"code": "VC7L2LBJVC", "credits": 100},
  {"code": "H088EG7EZ7", "credits": 100},
  {"code": "ONR4NTYVDJ", "credits": 100},
  {"code": "7DAZ6JIRWKY", "credits": 1000},
  {"code": "UPDTF6WM0V", "credits": 1000},
  {"code": "CV8OOANSK1Q", "credits": 1000},
  {"code": "OBPI2ZOTYN", "credits": 1000},
  {"code": "PYI0G4RZGWP", "credits": 1000},
  {"code": "X94LO3QX2SC", "credits": 1000},
  {"code": "YT2ARLN7FDJ", "credits": 1000},
  {"code": "D3ASYUQS4U6", "credits": 1000},
  {"code": "XGAAE7EHAUN", "credits": 1000},
  {"code": "JV8OXQAPG6M", "credits": 1000},
  {"code": "EZNJU38FAW", "credits": 1000},
  {"code": "83YHJC1T10B", "credits": 1000},
  {"code": "UFMQFA7ER2G", "credits": 1000},
  {"code": "99RHZWHKE8", "credits": 1000},
  {"code": "PBRYT09AZG", "credits": 1000},
  {"code": "44JBI2KHEJ9", "credits": 1000},
  {"code": "UHQZ3LPLKQ", "credits": 1000},
  {"code": "BGL5T2T74CC", "credits": 1000},
  {"code": "XMXPJG5MXLH", "credits": 1000},
  {"code": "AWBVGWOHR9D", "credits": 1000},
  {"code": "NI4I7JEQ66", "credits": 1000},
  {"code": "1K32YHHTGI7", "credits": 1000},
  {"code": "ZHVQ6EX9FQS", "credits": 1000},
  {"code": "MFOHOVV28ZD", "credits": 1000},
  {"code": "ZU07K70E6W", "credits": 1000},
  {"code": "LFWZ4JHV3R", "credits": 1000},
  {"code": "EKLTMRU48GU", "credits": 1000},
  {"code": "7J6R5S98OH2", "credits": 1000},
  {"code": "C2T6KX6KDF", "credits": 1000},
  {"code": "QRKHULV8UZK", "credits": 1000}
]
